np_nwb_trials/__init__.py
np_nwb_trials/nwb/__init__.py
np_nwb_trials/nwb/utils.py
np_nwb_trials/processing/DR_processing_script.py
np_nwb_trials/processing/DR_processing_utils.py
np_nwb_trials/processing/__init__.py
np_nwb_trials/processing/ecephys.py
np_nwb_trials/processing/probeSync.py
np_nwb_trials/processing/sync/MANIFEST.in
np_nwb_trials/processing/sync/README.md
np_nwb_trials/processing/sync/requirements.txt
np_nwb_trials/processing/sync/requirements_acq.txt
np_nwb_trials/processing/sync/requirements_dev.txt
np_nwb_trials/processing/sync/setup.py
np_nwb_trials/processing/sync/sync/__init__.py
np_nwb_trials/processing/sync/sync/dataset.py
np_nwb_trials/processing/sync/sync/gui/README.md
np_nwb_trials/processing/sync/sync/gui/__init__.py
np_nwb_trials/processing/sync/sync/gui/res/checkbox.png
np_nwb_trials/processing/sync/sync/gui/res/darkorange_stylesheet.css
np_nwb_trials/processing/sync/sync/gui/res/down_arrow.png
np_nwb_trials/processing/sync/sync/gui/res/handle.png
np_nwb_trials/processing/sync/sync/gui/res/record.png
np_nwb_trials/processing/sync/sync/gui/res/stop.png
np_nwb_trials/processing/sync/sync/gui/res/visualizer.ico
np_nwb_trials/processing/sync/sync/gui/res/visualizer.png
np_nwb_trials/processing/sync/sync/gui/sync_gui.py
np_nwb_trials/processing/sync/sync/gui/sync_gui.ui
np_nwb_trials/processing/sync/sync/gui/visualizer.py
np_nwb_trials/processing/sync/sync/ni/__init__.py
np_nwb_trials/processing/sync/sync/ni/daq.py
np_nwb_trials/processing/sync/sync/sync.py
np_nwb_trials/processing/sync/sync/tango/sync_device.py
np_nwb_trials/processing/sync/sync/utils/__init__.py
np_nwb_trials/processing/sync/sync/utils/h5.py
np_nwb_trials/processing/sync/sync/utils/recover.py
np_nwb_trials/processing/sync/sync/utils/sample.py
np_nwb_trials/processing/sync/sync/zro/__init__.py
np_nwb_trials/processing/sync/sync/zro/gui_interface.py
np_nwb_trials/processing/sync/sync/zro/sync_device.py
np_nwb_trials/processing/sync/sync.egg-info/PKG-INFO
np_nwb_trials/processing/sync/sync.egg-info/SOURCES.txt
np_nwb_trials/processing/sync/sync.egg-info/dependency_links.txt
np_nwb_trials/processing/sync/sync.egg-info/entry_points.txt
np_nwb_trials/processing/sync/sync.egg-info/top_level.txt
np_nwb_trials/processing/sync/tests/test_dataset.py
np_nwb_trials-0.3.0.dist-info/WHEEL
np_nwb_trials-0.3.0.dist-info/METADATA
np_nwb_trials-0.3.0.dist-info/RECORD
