Metadata-Version: 2.1
Name: np-nwb-trials
Version: 0.3.0
License: MIT
Author-email: Chris Mochizuki <chrism@alleninstitute.org>
Requires-Python: >=3.9
Requires-Dist: allensdk>=2.14.1
Requires-Dist: click>=8.1.3
Requires-Dist: pandera>=0.14.5
Requires-Dist: pynwb>=2.0.0
Requires-Dist: pytest>=7.3.1
Requires-Dist: python-dotenv>=1.0.0
Requires-Dist: pyyaml>=6.0
